termius/__init__.py
termius/app.py
termius/main.py
termius/account/__init__.py
termius/account/commands.py
termius/account/managers.py
termius/cloud/__init__.py
termius/cloud/commands.py
termius/cloud/client/__init__.py
termius/cloud/client/controllers.py
termius/cloud/client/cryptor.py
termius/cloud/client/transformers/__init__.py
termius/cloud/client/transformers/base.py
termius/cloud/client/transformers/many.py
termius/cloud/client/transformers/mixins.py
termius/cloud/client/transformers/single.py
termius/cloud/client/transformers/utils.py
termius/core/__init__.py
termius/core/api.py
termius/core/exceptions.py
termius/core/settings.py
termius/core/signals.py
termius/core/subscribers.py
termius/core/utils.py
termius/core/commands/__init__.py
termius/core/commands/arg_types.py
termius/core/commands/base.py
termius/core/commands/help.py
termius/core/commands/many.py
termius/core/commands/mixins.py
termius/core/commands/single.py
termius/core/commands/utils.py
termius/core/models/__init__.py
termius/core/models/base.py
termius/core/models/terminal.py
termius/core/models/utils.py
termius/core/storage/__init__.py
termius/core/storage/driver.py
termius/core/storage/idgenerators.py
termius/core/storage/operators.py
termius/core/storage/query.py
termius/core/storage/strategies.py
termius/formatters/__init__.py
termius/formatters/mixins.py
termius/formatters/ssh.py
termius/handlers/__init__.py
termius/handlers/connect.py
termius/handlers/group.py
termius/handlers/host.py
termius/handlers/identity.py
termius/handlers/info.py
termius/handlers/init.py
termius/handlers/pf_rule.py
termius/handlers/snippet.py
termius/handlers/ssh_config.py
termius/handlers/ssh_key.py
termius/handlers/tag.py
termius/handlers/taghost.py
termius/porting/__init__.py
termius/porting/commands.py
termius/porting/providers/__init__.py
termius/porting/providers/base.py
termius/porting/providers/securecrt/__init__.py
termius/porting/providers/securecrt/parser.py
termius-1.2.15.dist-info/AUTHORS
termius-1.2.15.dist-info/LICENSE
termius-1.2.15.dist-info/METADATA
termius-1.2.15.dist-info/WHEEL
termius-1.2.15.dist-info/entry_points.txt
termius-1.2.15.dist-info/top_level.txt
termius-1.2.15.dist-info/RECORD
