Metadata-Version: 2.1
Name: termius
Version: 1.2.15
Summary: Termius ssh-config utility.
Home-page: https://github.com/termius/termius-cli
Author: Termius Corporation
Author-email: hello@termius.com
License: BSD
Keywords: termius,crystalnix
Platform: UNKNOWN
Classifier: Development Status :: 4 - Beta
Classifier: Environment :: Console
Classifier: Intended Audience :: System Administrators
Classifier: Intended Audience :: Developers
Classifier: License :: OSI Approved :: BSD License
Classifier: Operating System :: Unix
Classifier: Programming Language :: Python :: 2.7
Classifier: Programming Language :: Python :: 3.5
Classifier: Programming Language :: Python :: 3.6
Classifier: Programming Language :: Python :: 3.7
Classifier: Programming Language :: Python :: 3.8
Classifier: Programming Language :: Python :: 3.9
Classifier: Topic :: Utilities
Requires-Dist: cliff (==2.7.0)
Requires-Dist: stevedore (>=1.10.0)
Requires-Dist: requests (>=2.7.0)
Requires-Dist: six (>=1.10.0)
Requires-Dist: ndg-httpsclient (>=0.4.0)
Requires-Dist: cached-property (>=1.3.0)
Requires-Dist: paramiko (>=1.16.0)
Requires-Dist: pathlib2 (>=2.1.0)
Requires-Dist: blinker (>=1.4)
Requires-Dist: google-measurement-protocol (==0.1.6)
Requires-Dist: pyopenssl (<=19.1.0,>=0.15.1) ; python_version == "2.7" or python_version == "3.5"
Requires-Dist: cryptography (==3.2) ; python_version == "3.5" or python_version == "2.7"
Requires-Dist: cryptography (>=3.2) ; python_version >= "3.6"
Requires-Dist: pyopenssl (>=0.15.1) ; python_version >= "3.6"
